setup.cfg
setup.py
src/wowlint/__init__.py
src/wowlint/_version.py
src/wowlint/command.py
src/wowlint/linter.py
src/wowlint/wowfile.py
src/wowlint.egg-info/PKG-INFO
src/wowlint.egg-info/SOURCES.txt
src/wowlint.egg-info/dependency_links.txt
src/wowlint.egg-info/entry_points.txt
src/wowlint.egg-info/requires.txt
src/wowlint.egg-info/top_level.txt
src/wowlint/validation/__init__.py
src/wowlint/validation/common.py
src/wowlint/validation/core.py
src/wowlint/validation/liturgy.py
src/wowlint/validation/songs.py