Metadata-Version: 1.0
Name: wowlint
Version: 0.2.0
Summary: Linter for Words of Worship resource files
Home-page: https://github.com/jamesremuscat/wowlint
Author: James Muscat
Author-email: jamesremuscat@gmail.com
License: UNKNOWN
Platform: UNKNOWN
